tests/_CC/CC.v
module CC  (
  input wire                   clk,    
  input wire                   reset,  
  input wire                   enable, 
  output wire [7:0] out  // data to read
);

reg [7:0] count;

assign out = count;


always @(posedge clk) begin

	if (reset) begin
		count <= 0;
	end 
	else if(enable)
	begin 
		count<=count+1;
	end

end 

endmodule

tests/_CC/TestCC.v
`timescale 1ns/1ps

module CC_bench;

reg enable;
reg reset;
reg clk;

wire [7:0] out;

CC CC_ (
	.enable(enable),
	.reset(reset),
	.clk(clk),
	.out(out));

	initial begin
		$dumpfile("CC.vcd");
		$dumpvars(0, CC_bench.CC_);
		clk = 0;
		reset = 1;
		#26 reset = 0;
		#500000 $finish;
	end

	always begin
		#25 clk = ~clk;
	end

	always begin
		#24;
		enable = $random;
		#26;
	end
endmodule

tests/_CC/CC.vcd
$date
	Tue May 23 13:16:37 2017
$end
$version
	QuestaSim Version 10.6_1
$end
$timescale
	1ps
$end

$scope module CC_bench $end

$scope module CC_ $end
$var wire 1 ! clk $end
$var wire 1 " reset $end
$var wire 1 # enable $end
$var wire 1 $ out [7] $end
$var wire 1 % out [6] $end
$var wire 1 & out [5] $end
$var wire 1 ' out [4] $end
$var wire 1 ( out [3] $end
$var wire 1 ) out [2] $end
$var wire 1 * out [1] $end
$var wire 1 + out [0] $end
$var reg 8 , count [7:0] $end
$upscope $end
$upscope $end
$enddefinitions $end
#0
$dumpvars
bx ,
x+
x*
x)
x(
x'
x&
x%
x$
x#
1"
0!
$end
#24000
0#
#25000
1!
b0 ,
0+
0*
0)
0(
0'
0&
0%
0$
#26000
0"
#50000
0!
#74000
1#
#75000
1!
b1 ,
1+
#100000
0!
#125000
1!
b10 ,
0+
1*
#150000
0!
#175000
1!
b11 ,
1+
#200000
0!
#225000
1!
b100 ,
0+
0*
1)
#250000
0!
#275000
1!
b101 ,
1+
#300000
0!
#325000
1!
b110 ,
0+
1*
#350000
0!
#374000
0#
#375000
1!
#400000
0!
#424000
1#
#425000
1!
b111 ,
1+
#450000
0!
#475000
1!
b1000 ,
0+
0*
0)
1(
#500000
0!
#524000
0#
#525000
1!
#550000
0!
#574000
1#
#575000
1!
b1001 ,
1+
#600000
0!
#625000
1!
b1010 ,
0+
1*
#650000
0!
#674000
0#
#675000
1!
#700000
0!
#724000
1#
#725000
1!
b1011 ,
1+
#750000
0!
#774000
0#
#775000
1!
#800000
0!
#824000
1#
#825000
1!
b1100 ,
0+
0*
1)
#850000
0!
#874000
0#
#875000
1!
#900000
0!
#924000
1#
#925000
1!
b1101 ,
1+
#950000
0!
#975000
1!
b1110 ,
0+
1*
#1000000
0!
#1024000
0#
#1025000
1!
#1050000
0!
#1074000
1#
#1075000
1!
b1111 ,
1+
#1100000
0!
#1124000
0#
#1125000
1!
#1150000
0!
#1175000
1!
#1200000
0!
#1225000
1!
#1250000
0!
#1274000
1#
#1275000
1!
b10000 ,
0+
0*
0)
0(
1'
#1300000
0!
#1324000
0#
#1325000
1!
#1350000
0!
#1374000
1#
#1375000
1!
b10001 ,
1+
#1400000
0!
#1425000
1!
b10010 ,
0+
1*
#1450000
0!
#1475000
1!
b10011 ,
1+
#1500000
0!
#1525000
1!
b10100 ,
0+
0*
1)
#1550000
0!
#1574000
0#
#1575000
1!
#1600000
0!
#1625000
1!
#1650000
0!
#1675000
1!
#1700000
0!
#1725000
1!
#1750000
0!
#1774000
1#
#1775000
1!
b10101 ,
1+
#1800000
0!
#1824000
0#
#1825000
1!
#1850000
0!
#1874000
1#
#1875000
1!
b10110 ,
0+
1*
#1900000
0!
#1925000
1!
b10111 ,
1+
#1950000
0!
#1975000
1!
b11000 ,
0+
0*
0)
1(
#2000000
0!
#2025000
1!
b11001 ,
1+
#2050000
0!
#2075000
1!
b11010 ,
0+
1*
#2100000
0!
#2124000
0#
#2125000
1!
#2150000
0!
#2175000
1!
#2200000
0!
#2224000
1#
#2225000
1!
b11011 ,
1+
#2250000
0!
#2275000
1!
b11100 ,
0+
0*
1)
#2300000
0!
#2325000
1!
b11101 ,
1+
#2350000
0!
#2374000
0#
#2375000
1!
#2400000
0!
#2425000
1!
#2450000
0!
#2475000
1!
#2500000
0!
#2525000
1!
#2550000
0!
#2575000
1!
#2600000
0!
#2624000
1#
#2625000
1!
b11110 ,
0+
1*
#2650000
0!
#2674000
0#
#2675000
1!
#2700000
0!
#2725000
1!
#2750000
0!
#2774000
1#
#2775000
1!
b11111 ,
1+
#2800000
0!
#2825000
1!
b100000 ,
0+
0*
0)
0(
0'
1&
#2850000
0!
#2874000
0#
#2875000
1!
#2900000
0!
#2925000
1!
#2950000
0!
#2975000
1!
#3000000
0!
#3025000
1!
#3050000
0!
#3075000
1!
#3100000
0!
#3124000
1#
#3125000
1!
b100001 ,
1+
#3150000
0!
#3175000
1!
b100010 ,
0+
1*
#3200000
0!
#3225000
1!
b100011 ,
1+
#3250000
0!
#3275000
1!
b100100 ,
0+
0*
1)
#3300000
0!
#3325000
1!
b100101 ,
1+
#3350000
0!
#3374000
0#
#3375000
1!
#3400000
0!
#3425000
1!
#3450000
0!
#3474000
1#
#3475000
1!
b100110 ,
0+
1*
#3500000
0!
#3525000
1!
b100111 ,
1+
#3550000
0!
#3575000
1!
b101000 ,
0+
0*
0)
1(
#3600000
0!
#3624000
0#
#3625000
1!
#3650000
0!
#3675000
1!
#3700000
0!
#3724000
1#
#3725000
1!
b101001 ,
1+
#3750000
0!
#3775000
1!
b101010 ,
0+
1*
#3800000
0!
#3824000
0#
#3825000
1!
#3850000
0!
#3874000
1#
#3875000
1!
b101011 ,
1+
#3900000
0!
#3925000
1!
b101100 ,
0+
0*
1)
#3950000
0!
#3974000
0#
#3975000
1!
#4000000
0!
#4024000
1#
#4025000
1!
b101101 ,
1+
#4050000
0!
#4075000
1!
b101110 ,
0+
1*
#4100000
0!
#4125000
1!
b101111 ,
1+
#4150000
0!
#4174000
0#
#4175000
1!
#4200000
0!
#4224000
1#
#4225000
1!
b110000 ,
0+
0*
0)
0(
1'
#4250000
0!
#4275000
1!
b110001 ,
1+
#4300000
0!
#4324000
0#
#4325000
1!
#4350000
0!
#4375000
1!
#4400000
0!
#4425000
1!
#4450000
0!
#4475000
1!
#4500000
0!
#4524000
1#
#4525000
1!
b110010 ,
0+
1*
#4550000
0!
#4575000
1!
b110011 ,
1+
#4600000
0!
#4624000
0#
#4625000
1!
#4650000
0!
#4675000
1!
#4700000
0!
#4724000
1#
#4725000
1!
b110100 ,
0+
0*
1)
#4750000
0!
#4775000
1!
b110101 ,
1+
#4800000
0!
#4825000
1!
b110110 ,
0+
1*
#4850000
0!
#4875000
1!
b110111 ,
1+
#4900000
0!
#4925000
1!
b111000 ,
0+
0*
0)
1(
#4950000
0!
#4974000
0#
#4975000
1!
#5000000
0!
#5024000
1#
#5025000
1!
b111001 ,
1+
#5050000
0!
#5075000
1!
b111010 ,
0+
1*
#5100000
0!
#5125000
1!
b111011 ,
1+
#5150000
0!
#5174000
0#
#5175000
1!
#5200000
0!
#5225000
1!
#5250000
0!
#5275000
1!
#5300000
0!
#5325000
1!
#5350000
0!
#5375000
1!
#5400000
0!
#5425000
1!
#5450000
0!
#5475000
1!
#5500000
0!
#5524000
1#
#5525000
1!
b111100 ,
0+
0*
1)
#5550000
0!
#5575000
1!
b111101 ,
1+
#5600000
0!
#5625000
1!
b111110 ,
0+
1*
#5650000
0!
#5675000
1!
b111111 ,
1+
#5700000
0!
#5725000
1!
b1000000 ,
0+
0*
0)
0(
0'
0&
1%
#5750000
0!
#5774000
0#
#5775000
1!
#5800000
0!
#5824000
1#
#5825000
1!
b1000001 ,
1+
#5850000
0!
#5875000
1!
b1000010 ,
0+
1*
#5900000
0!
#5924000
0#
#5925000
1!
#5950000
0!
#5975000
1!
#6000000
0!
#6024000
1#
#6025000
1!
b1000011 ,
1+
#6050000
0!
#6075000
1!
b1000100 ,
0+
0*
1)
#6100000
0!
#6124000
0#
#6125000
1!
#6150000
0!
#6174000
1#
#6175000
1!
b1000101 ,
1+
#6200000
0!
#6225000
1!
b1000110 ,
0+
1*
#6250000
0!
#6275000
1!
b1000111 ,
1+
#6300000
0!
#6325000
1!
b1001000 ,
0+
0*
0)
1(
#6350000
0!
#6374000
0#
#6375000
1!
#6400000
0!
#6425000
1!
#6450000
0!
#6475000
1!
#6500000
0!
#6524000
1#
#6525000
1!
b1001001 ,
1+
#6550000
0!
#6574000
0#
#6575000
1!
#6600000
0!
#6625000
1!
#6650000
0!
#6675000
1!
#6700000
0!
#6724000
1#
#6725000
1!
b1001010 ,
0+
1*
#6750000
0!
#6775000
1!
b1001011 ,
1+
#6800000
0!
#6824000
0#
#6825000
1!
#6850000
0!
#6875000
1!
#6900000
0!
#6924000
1#
#6925000
1!
b1001100 ,
0+
0*
1)
#6950000
0!
#6974000
0#
#6975000
1!
#7000000
0!
#7025000
1!
#7050000
0!
#7075000
1!
#7100000
0!
#7124000
1#
#7125000
1!
b1001101 ,
1+
#7150000
0!
#7174000
0#
#7175000
1!
#7200000
0!
#7225000
1!
#7250000
0!
#7274000
1#
#7275000
1!
b1001110 ,
0+
1*
#7300000
0!
#7324000
0#
#7325000
1!
#7350000
0!
#7374000
1#
#7375000
1!
b1001111 ,
1+
#7400000
0!
#7425000
1!
b1010000 ,
0+
0*
0)
0(
1'
#7450000
0!
#7475000
1!
b1010001 ,
1+
#7500000
0!
#7525000
1!
b1010010 ,
0+
1*
#7550000
0!
#7575000
1!
b1010011 ,
1+
#7600000
0!
#7624000
0#
#7625000
1!
#7650000
0!
#7675000
1!
#7700000
0!
#7725000
1!
#7750000
0!
#7774000
1#
#7775000
1!
b1010100 ,
0+
0*
1)
#7800000
0!
#7824000
0#
#7825000
1!
#7850000
0!
#7875000
1!
#7900000
0!
#7924000
1#
#7925000
1!
b1010101 ,
1+
#7950000
0!
#7975000
1!
b1010110 ,
0+
1*
#8000000
0!
#8024000
0#
#8025000
1!
#8050000
0!
#8075000
1!
#8100000
0!
#8125000
1!
#8150000
0!
#8174000
1#
#8175000
1!
b1010111 ,
1+
#8200000
0!
#8225000
1!
b1011000 ,
0+
0*
0)
1(
#8250000
0!
#8274000
0#
#8275000
1!
#8300000
0!
#8325000
1!
#8350000
0!
#8375000
1!
#8400000
0!
#8424000
1#
#8425000
1!
b1011001 ,
1+
#8450000
0!
#8475000
1!
b1011010 ,
0+
1*
#8500000
0!
#8524000
0#
#8525000
1!
#8550000
0!
#8575000
1!
#8600000
0!
#8625000
1!
#8650000
0!
#8674000
1#
#8675000
1!
b1011011 ,
1+
#8700000
0!
#8724000
0#
#8725000
1!
#8750000
0!
#8775000
1!
#8800000
0!
#8824000
1#
#8825000
1!
b1011100 ,
0+
0*
1)
#8850000
0!
#8874000
0#
#8875000
1!
#8900000
0!
#8925000
1!
#8950000
0!
#8975000
1!
#9000000
0!
#9024000
1#
#9025000
1!
b1011101 ,
1+
#9050000
0!
#9074000
0#
#9075000
1!
#9100000
0!
#9124000
1#
#9125000
1!
b1011110 ,
0+
1*
#9150000
0!
#9175000
1!
b1011111 ,
1+
#9200000
0!
#9224000
0#
#9225000
1!
#9250000
0!
#9275000
1!
#9300000
0!
#9325000
1!
#9350000
0!
#9375000
1!
#9400000
0!
#9424000
1#
#9425000
1!
b1100000 ,
0+
0*
0)
0(
0'
1&
#9450000
0!
#9474000
0#
#9475000
1!
#9500000
0!
#9525000
1!
#9550000
0!
#9575000
1!
#9600000
0!
#9625000
1!
#9650000
0!
#9674000
1#
#9675000
1!
b1100001 ,
1+
#9700000
0!
#9725000
1!
b1100010 ,
0+
1*
#9750000
0!
#9775000
1!
b1100011 ,
1+
#9800000
0!
#9824000
0#
#9825000
1!
#9850000
0!
#9874000
1#
#9875000
1!
b1100100 ,
0+
0*
1)
#9900000
0!
#9925000
1!
b1100101 ,
1+
#9950000
0!
#9975000
1!
b1100110 ,
0+
1*
#10000000
0!
#10024000
0#
#10025000
1!
#10050000
0!
#10075000
1!
#10100000
0!
#10124000
1#
#10125000
1!
b1100111 ,
1+
#10150000
0!
#10175000
1!
b1101000 ,
0+
0*
0)
1(
#10200000
0!
#10225000
1!
b1101001 ,
1+
#10250000
0!
#10275000
1!
b1101010 ,
0+
1*
#10300000
0!
#10325000
1!
b1101011 ,
1+
#10350000
0!
#10374000
0#
#10375000
1!
#10400000
0!
#10424000
1#
#10425000
1!
b1101100 ,
0+
0*
1)
#10450000
0!
#10475000
1!
b1101101 ,
1+
#10500000
0!
#10524000
0#
#10525000
1!
#10550000
0!
#10575000
1!
#10600000
0!
#10625000
1!
#10650000
0!
#10675000
1!
#10700000
0!
#10724000
1#
#10725000
1!
b1101110 ,
0+
1*
#10750000
0!
#10775000
1!
b1101111 ,
1+
#10800000
0!
#10824000
0#
#10825000
1!
#10850000
0!
#10875000
1!
#10900000
0!
#10924000
1#
#10925000
1!
b1110000 ,
0+
0*
0)
0(
1'
#10950000
0!
#10974000
0#
#10975000
1!
#11000000
0!
#11025000
1!
#11050000
0!
#11074000
1#
#11075000
1!
b1110001 ,
1+
#11100000
0!
#11124000
0#
#11125000
1!
#11150000
0!
#11175000
1!
#11200000
0!
#11224000
1#
#11225000
1!
b1110010 ,
0+
1*
#11250000
0!
#11274000
0#
#11275000
1!
#11300000
0!
#11325000
1!
#11350000
0!
#11374000
1#
#11375000
1!
b1110011 ,
1+
#11400000
0!
#11425000
1!
b1110100 ,
0+
0*
1)
#11450000
0!
#11475000
1!
b1110101 ,
1+
#11500000
0!
#11524000
0#
#11525000
1!
#11550000
0!
#11575000
1!
#11600000
0!
#11625000
1!
#11650000
0!
#11674000
1#
#11675000
1!
b1110110 ,
0+
1*
#11700000
0!
#11724000
0#
#11725000
1!
#11750000
0!
#11775000
1!
#11800000
0!
#11824000
1#
#11825000
1!
b1110111 ,
1+
#11850000
0!
#11874000
0#
#11875000
1!
#11900000
0!
#11925000
1!
#11950000
0!
#11975000
1!
#12000000
0!
#12025000
1!
#12050000
0!
#12074000
1#
#12075000
1!
b1111000 ,
0+
0*
0)
1(
#12100000
0!
#12124000
0#
#12125000
1!
#12150000
0!
#12175000
1!
#12200000
0!
#12225000
1!
#12250000
0!
#12274000
1#
#12275000
1!
b1111001 ,
1+
#12300000
0!
#12325000
1!
b1111010 ,
0+
1*
#12350000
0!
#12374000
0#
#12375000
1!
#12400000
0!
#12424000
1#
#12425000
1!
b1111011 ,
1+
#12450000
0!
#12475000
1!
b1111100 ,
0+
0*
1)
#12500000
0!
#12525000
1!
b1111101 ,
1+
#12550000
0!
#12575000
1!
b1111110 ,
0+
1*
#12600000
0!
#12624000
0#
#12625000
1!
#12650000
0!
#12674000
1#
#12675000
1!
b1111111 ,
1+
#12700000
0!
#12725000
1!
b10000000 ,
0+
0*
0)
0(
0'
0&
0%
1$
#12750000
0!
#12775000
1!
b10000001 ,
1+
#12800000
0!
#12824000
0#
#12825000
1!
#12850000
0!
#12875000
1!
#12900000
0!
#12924000
1#
#12925000
1!
b10000010 ,
0+
1*
#12950000
0!
#12974000
0#
#12975000
1!
#13000000
0!
#13025000
1!
#13050000
0!
#13074000
1#
#13075000
1!
b10000011 ,
1+
#13100000
0!
#13125000
1!
b10000100 ,
0+
0*
1)
#13150000
0!
#13174000
0#
#13175000
1!
#13200000
0!
#13225000
1!
#13250000
0!
#13274000
1#
#13275000
1!
b10000101 ,
1+
#13300000
0!
#13324000
0#
#13325000
1!
#13350000
0!
#13375000
1!
#13400000
0!
#13424000
1#
#13425000
1!
b10000110 ,
0+
1*
#13450000
0!
#13474000
0#
#13475000
1!
#13500000
0!
#13524000
1#
#13525000
1!
b10000111 ,
1+
#13550000
0!
#13575000
1!
b10001000 ,
0+
0*
0)
1(
#13600000
0!
#13624000
0#
#13625000
1!
#13650000
0!
#13674000
1#
#13675000
1!
b10001001 ,
1+
#13700000
0!
#13724000
0#
#13725000
1!
#13750000
0!
#13774000
1#
#13775000
1!
b10001010 ,
0+
1*
#13800000
0!
#13824000
0#
#13825000
1!
#13850000
0!
#13875000
1!
#13900000
0!
#13924000
1#
#13925000
1!
b10001011 ,
1+
#13950000
0!
#13974000
0#
#13975000
1!
#14000000
0!
#14025000
1!
#14050000
0!
#14075000
1!
#14100000
0!
#14124000
1#
#14125000
1!
b10001100 ,
0+
0*
1)
#14150000
0!
#14175000
1!
b10001101 ,
1+
#14200000
0!
#14225000
1!
b10001110 ,
0+
1*
#14250000
0!
#14275000
1!
b10001111 ,
1+
#14300000
0!
#14325000
1!
b10010000 ,
0+
0*
0)
0(
1'
#14350000
0!
#14374000
0#
#14375000
1!
#14400000
0!
#14424000
1#
#14425000
1!
b10010001 ,
1+
#14450000
0!
#14475000
1!
b10010010 ,
0+
1*
#14500000
0!
#14525000
1!
b10010011 ,
1+
#14550000
0!
#14574000
0#
#14575000
1!
#14600000
0!
#14625000
1!
#14650000
0!
#14675000
1!
#14700000
0!
#14725000
1!
#14750000
0!
#14775000
1!
#14800000
0!
#14825000
1!
#14850000
0!
#14874000
1#
#14875000
1!
b10010100 ,
0+
0*
1)
#14900000
0!
#14925000
1!
b10010101 ,
1+
#14950000
0!
#14975000
1!
b10010110 ,
0+
1*
#15000000
0!
#15025000
1!
b10010111 ,
1+
#15050000
0!
#15075000
1!
b10011000 ,
0+
0*
0)
1(
#15100000
0!
#15125000
1!
b10011001 ,
1+
#15150000
0!
#15175000
1!
b10011010 ,
0+
1*
#15200000
0!
#15224000
0#
#15225000
1!
#15250000
0!
#15274000
1#
#15275000
1!
b10011011 ,
1+
#15300000
0!
#15325000
1!
b10011100 ,
0+
0*
1)
#15350000
0!
#15375000
1!
b10011101 ,
1+
#15400000
0!
#15425000
1!
b10011110 ,
0+
1*
#15450000
0!
#15475000
1!
b10011111 ,
1+
#15500000
0!
#15525000
1!
b10100000 ,
0+
0*
0)
0(
0'
1&
#15550000
0!
#15575000
1!
b10100001 ,
1+
#15600000
0!
#15625000
1!
b10100010 ,
0+
1*
#15650000
0!
#15674000
0#
#15675000
1!
#15700000
0!
#15725000
1!
#15750000
0!
#15774000
1#
#15775000
1!
b10100011 ,
1+
#15800000
0!
#15825000
1!
b10100100 ,
0+
0*
1)
#15850000
0!
#15874000
0#
#15875000
1!
#15900000
0!
#15925000
1!
#15950000
0!
#15975000
1!
#16000000
0!
#16025000
1!
#16050000
0!
#16074000
1#
#16075000
1!
b10100101 ,
1+
#16100000
0!
#16124000
0#
#16125000
1!
#16150000
0!
#16175000
1!
#16200000
0!
#16225000
1!
#16250000
0!
#16275000
1!
#16300000
0!
#16325000
1!
#16350000
0!
#16375000
1!
#16400000
0!
#16424000
1#
#16425000
1!
b10100110 ,
0+
1*
#16450000
0!
#16474000
0#
#16475000
1!
#16500000
0!
#16525000
1!
#16550000
0!
#16574000
1#
#16575000
1!
b10100111 ,
1+
#16600000
0!
#16624000
0#
#16625000
1!
#16650000
0!
#16675000
1!
#16700000
0!
#16725000
1!
#16750000
0!
#16775000
1!
#16800000
0!
#16824000
1#
#16825000
1!
b10101000 ,
0+
0*
0)
1(
#16850000
0!
#16875000
1!
b10101001 ,
1+
#16900000
0!
#16925000
1!
b10101010 ,
0+
1*
#16950000
0!
#16975000
1!
b10101011 ,
1+
#17000000
0!
#17025000
1!
b10101100 ,
0+
0*
1)
#17050000
0!
#17074000
0#
#17075000
1!
#17100000
0!
#17124000
1#
#17125000
1!
b10101101 ,
1+
#17150000
0!
#17175000
1!
b10101110 ,
0+
1*
#17200000
0!
#17225000
1!
b10101111 ,
1+
#17250000
0!
#17274000
0#
#17275000
1!
#17300000
0!
#17324000
1#
#17325000
1!
b10110000 ,
0+
0*
0)
0(
1'
#17350000
0!
#17374000
0#
#17375000
1!
#17400000
0!
#17425000
1!
#17450000
0!
#17474000
1#
#17475000
1!
b10110001 ,
1+
#17500000
0!
#17525000
1!
b10110010 ,
0+
1*
#17550000
0!
#17574000
0#
#17575000
1!
#17600000
0!
#17624000
1#
#17625000
1!
b10110011 ,
1+
#17650000
0!
#17674000
0#
#17675000
1!
#17700000
0!
#17725000
1!
#17750000
0!
#17774000
1#
#17775000
1!
b10110100 ,
0+
0*
1)
#17800000
0!
#17824000
0#
#17825000
1!
#17850000
0!
#17875000
1!
#17900000
0!
#17925000
1!
#17950000
0!
#17975000
1!
#18000000
0!
#18024000
1#
#18025000
1!
b10110101 ,
1+
#18050000
0!
#18075000
1!
b10110110 ,
0+
1*
#18100000
0!
#18125000
1!
b10110111 ,
1+
#18150000
0!
#18175000
1!
b10111000 ,
0+
0*
0)
1(
#18200000
0!
#18224000
0#
#18225000
1!
#18250000
0!
#18274000
1#
#18275000
1!
b10111001 ,
1+
#18300000
0!
#18325000
1!
b10111010 ,
0+
1*
#18350000
0!
#18375000
1!
b10111011 ,
1+
#18400000
0!
#18425000
1!
b10111100 ,
0+
0*
1)
#18450000
0!
#18475000
1!
b10111101 ,
1+
#18500000
0!
#18525000
1!
b10111110 ,
0+
1*
#18550000
0!
#18575000
1!
b10111111 ,
1+
#18600000
0!
#18624000
0#
#18625000
1!
#18650000
0!
#18674000
1#
#18675000
1!
b11000000 ,
0+
0*
0)
0(
0'
0&
1%
#18700000
0!
#18724000
0#
#18725000
1!
#18750000
0!
#18774000
1#
#18775000
1!
b11000001 ,
1+
#18800000
0!
#18824000
0#
#18825000
1!
#18850000
0!
#18875000
1!
#18900000
0!
#18924000
1#
#18925000
1!
b11000010 ,
0+
1*
#18950000
0!
#18974000
0#
#18975000
1!
#19000000
0!
#19025000
1!
#19050000
0!
#19075000
1!
#19100000
0!
#19125000
1!
#19150000
0!
#19175000
1!
#19200000
0!
#19224000
1#
#19225000
1!
b11000011 ,
1+
#19250000
0!
#19274000
0#
#19275000
1!
#19300000
0!
#19325000
1!
#19350000
0!
#19375000
1!
#19400000
0!
#19425000
1!
#19450000
0!
#19475000
1!
#19500000
0!
#19525000
1!
#19550000
0!
#19574000
1#
#19575000
1!
b11000100 ,
0+
0*
1)
#19600000
0!
#19624000
0#
#19625000
1!
#19650000
0!
#19674000
1#
#19675000
1!
b11000101 ,
1+
#19700000
0!
#19724000
0#
#19725000
1!
#19750000
0!
#19775000
1!
#19800000
0!
#19824000
1#
#19825000
1!
b11000110 ,
0+
1*
#19850000
0!
#19874000
0#
#19875000
1!
#19900000
0!
#19924000
1#
#19925000
1!
b11000111 ,
1+
#19950000
0!
#19975000
1!
b11001000 ,
0+
0*
0)
1(
#20000000
0!
#20024000
0#
#20025000
1!
#20050000
0!
#20074000
1#
#20075000
1!
b11001001 ,
1+
#20100000
0!
#20124000
0#
#20125000
1!
#20150000
0!
#20174000
1#
#20175000
1!
b11001010 ,
0+
1*
#20200000
0!
#20224000
0#
#20225000
1!
#20250000
0!
#20275000
1!
#20300000
0!
#20325000
1!
#20350000
0!
#20375000
1!
#20400000
0!
#20424000
1#
#20425000
1!
b11001011 ,
1+
#20450000
0!
#20474000
0#
#20475000
1!
#20500000
0!
#20524000
1#
#20525000
1!
b11001100 ,
0+
0*
1)
#20550000
0!
#20574000
0#
#20575000
1!
#20600000
0!
#20624000
1#
#20625000
1!
b11001101 ,
1+
#20650000
0!
#20675000
1!
b11001110 ,
0+
1*
#20700000
0!
#20724000
0#
#20725000
1!
#20750000
0!
#20774000
1#
#20775000
1!
b11001111 ,
1+
#20800000
0!
#20824000
0#
#20825000
1!
#20850000
0!
#20874000
1#
#20875000
1!
b11010000 ,
0+
0*
0)
0(
1'
#20900000
0!
#20925000
1!
b11010001 ,
1+
#20950000
0!
#20975000
1!
b11010010 ,
0+
1*
#21000000
0!
#21024000
0#
#21025000
1!
#21050000
0!
#21074000
1#
#21075000
1!
b11010011 ,
1+
#21100000
0!
#21125000
1!
b11010100 ,
0+
0*
1)
#21150000
0!
#21174000
0#
#21175000
1!
#21200000
0!
#21225000
1!
#21250000
0!
#21274000
1#
#21275000
1!
b11010101 ,
1+
#21300000
0!
#21325000
1!
b11010110 ,
0+
1*
#21350000
0!
#21374000
0#
#21375000
1!
#21400000
0!
#21425000
1!
#21450000
0!
#21474000
1#
#21475000
1!
b11010111 ,
1+
#21500000
0!
#21525000
1!
b11011000 ,
0+
0*
0)
1(
#21550000
0!
#21574000
0#
#21575000
1!
#21600000
0!
#21625000
1!
#21650000
0!
#21674000
1#
#21675000
1!
b11011001 ,
1+
#21700000
0!
#21724000
0#
#21725000
1!
#21750000
0!
#21775000
1!
#21800000
0!
#21824000
1#
#21825000
1!
b11011010 ,
0+
1*
#21850000
0!
#21875000
1!
b11011011 ,
1+
#21900000
0!
#21924000
0#
#21925000
1!
#21950000
0!
#21975000
1!
#22000000
0!
#22024000
1#
#22025000
1!
b11011100 ,
0+
0*
1)
#22050000
0!
#22074000
0#
#22075000
1!
#22100000
0!
#22125000
1!
#22150000
0!
#22174000
1#
#22175000
1!
b11011101 ,
1+
#22200000
0!
#22225000
1!
b11011110 ,
0+
1*
#22250000
0!
#22274000
0#
#22275000
1!
#22300000
0!
#22324000
1#
#22325000
1!
b11011111 ,
1+
#22350000
0!
#22374000
0#
#22375000
1!
#22400000
0!
#22424000
1#
#22425000
1!
b11100000 ,
0+
0*
0)
0(
0'
1&
#22450000
0!
#22475000
1!
b11100001 ,
1+
#22500000
0!
#22524000
0#
#22525000
1!
#22550000
0!
#22574000
1#
#22575000
1!
b11100010 ,
0+
1*
#22600000
0!
#22625000
1!
b11100011 ,
1+
#22650000
0!
#22675000
1!
b11100100 ,
0+
0*
1)
#22700000
0!
#22724000
0#
#22725000
1!
#22750000
0!
#22774000
1#
#22775000
1!
b11100101 ,
1+
#22800000
0!
#22825000
1!
b11100110 ,
0+
1*
#22850000
0!
#22875000
1!
b11100111 ,
1+
#22900000
0!
#22924000
0#
#22925000
1!
#22950000
0!
#22975000
1!
#23000000
0!
#23024000
1#
#23025000
1!
b11101000 ,
0+
0*
0)
1(
#23050000
0!
#23074000
0#
#23075000
1!
#23100000
0!
#23125000
1!
#23150000
0!
#23174000
1#
#23175000
1!
b11101001 ,
1+
#23200000
0!
#23224000
0#
#23225000
1!
#23250000
0!
#23275000
1!
#23300000
0!
#23324000
1#
#23325000
1!
b11101010 ,
0+
1*
#23350000
0!
#23375000
1!
b11101011 ,
1+
#23400000
0!
#23424000
0#
#23425000
1!
#23450000
0!
#23474000
1#
#23475000
1!
b11101100 ,
0+
0*
1)
#23500000
0!
#23524000
0#
#23525000
1!
#23550000
0!
#23574000
1#
#23575000
1!
b11101101 ,
1+
#23600000
0!
#23625000
1!
b11101110 ,
0+
1*
#23650000
0!
#23675000
1!
b11101111 ,
1+
#23700000
0!
#23725000
1!
b11110000 ,
0+
0*
0)
0(
1'
#23750000
0!
#23774000
0#
#23775000
1!
#23800000
0!
#23825000
1!
#23850000
0!
#23874000
1#
#23875000
1!
b11110001 ,
1+
#23900000
0!
#23924000
0#
#23925000
1!
#23950000
0!
#23974000
1#
#23975000
1!
b11110010 ,
0+
1*
#24000000
0!
#24024000
0#
#24025000
1!
#24050000
0!
#24074000
1#
#24075000
1!
b11110011 ,
1+
#24100000
0!
#24125000
1!
b11110100 ,
0+
0*
1)
#24150000
0!
#24174000
0#
#24175000
1!
#24200000
0!
#24225000
1!
#24250000
0!
#24274000
1#
#24275000
1!
b11110101 ,
1+
#24300000
0!
#24325000
1!
b11110110 ,
0+
1*
#24350000
0!
#24375000
1!
b11110111 ,
1+
#24400000
0!
#24424000
0#
#24425000
1!
#24450000
0!
#24475000
1!
#24500000
0!
#24524000
1#
#24525000
1!
b11111000 ,
0+
0*
0)
1(
#24550000
0!
#24574000
0#
#24575000
1!
#24600000
0!
#24625000
1!
#24650000
0!
#24674000
1#
#24675000
1!
b11111001 ,
1+
#24700000
0!
#24725000
1!
b11111010 ,
0+
1*
#24750000
0!
#24775000
1!
b11111011 ,
1+
#24800000
0!
#24824000
0#
#24825000
1!
#24850000
0!
#24874000
1#
#24875000
1!
b11111100 ,
0+
0*
1)
#24900000
0!
#24925000
1!
b11111101 ,
1+
#24950000
0!
#24974000
0#
#24975000
1!
#25000000
0!
#25025000
1!
#25050000
0!
#25075000
1!
#25100000
0!
#25124000
1#
#25125000
1!
b11111110 ,
0+
1*
#25150000
0!
#25175000
1!
b11111111 ,
1+
#25200000
0!
#25225000
1!
b0 ,
0+
0*
0)
0(
0'
0&
0%
0$
#25250000
0!
#25274000
0#
#25275000
1!
#25300000
0!
#25325000
1!
#25350000
0!
#25375000
1!
#25400000
0!
#25424000
1#
#25425000
1!
b1 ,
1+
#25450000
0!
#25475000
1!
b10 ,
0+
1*
#25500000
0!
#25525000
1!
b11 ,
1+
#25550000
0!
#25575000
1!
b100 ,
0+
0*
1)
#25600000
0!
#25624000
0#
#25625000
1!
#25650000
0!
#25674000
1#
#25675000
1!
b101 ,
1+
#25700000
0!
#25725000
1!
b110 ,
0+
1*
#25750000
0!
#25775000
1!
b111 ,
1+
#25800000
0!
#25825000
1!
b1000 ,
0+
0*
0)
1(
#25850000
0!
#25875000
1!
b1001 ,
1+
#25900000
0!
#25925000
1!
b1010 ,
0+
1*
#25950000
0!
#25975000
1!
b1011 ,
1+
#26000000
0!
#26024000
0#
#26025000
1!
#26050000
0!
#26074000
1#
#26075000
1!
b1100 ,
0+
0*
1)
#26100000
0!
#26124000
0#
#26125000
1!
#26150000
0!
#26175000
1!
#26200000
0!
#26225000
1!
#26250000
0!
#26274000
1#
#26275000
1!
b1101 ,
1+
#26300000
0!
#26325000
1!
b1110 ,
0+
1*
#26350000
0!
#26375000
1!
b1111 ,
1+
#26400000
0!
#26425000
1!
b10000 ,
0+
0*
0)
0(
1'
#26450000
0!
#26475000
1!
b10001 ,
1+
#26500000
0!
#26525000
1!
b10010 ,
0+
1*
#26550000
0!
#26575000
1!
b10011 ,
1+
#26600000
0!
#26625000
1!
b10100 ,
0+
0*
1)
#26650000
0!
